empinken/__init__.py
empinken/static/empinken.yaml
empinken/static/index.js
nb_extension_empinken-0.0.7.data/data/etc/jupyter/nbconfig/notebook.d/empinken.json
nb_extension_empinken-0.0.7.data/data/share/jupyter/nbextensions/empinken/empinken.yaml
nb_extension_empinken-0.0.7.data/data/share/jupyter/nbextensions/empinken/index.js
nb_extension_empinken-0.0.7.dist-info/LICENSE
nb_extension_empinken-0.0.7.dist-info/METADATA
nb_extension_empinken-0.0.7.dist-info/WHEEL
nb_extension_empinken-0.0.7.dist-info/top_level.txt
nb_extension_empinken-0.0.7.dist-info/RECORD
