Metadata-Version: 2.1
Name: nb-extension-empinken
Version: 0.0.7
Summary: Empinken cell background colouring for class and nbclassic Jupyter notebooks.
Home-page: https://github.com/innovationOUtside/nb_extension_empinken
Author: Tony Hirst
Author-email: tony.hirst@gmail.com
License: MIT
License-File: LICENSE
Requires-Dist: jupyter-nbextensions-configurator
